AUTHORS.rst
LICENSE
MANIFEST.in
README.rst
requirements.txt
setup.py
test_fut14.py
fut14/EAHashingAlgorithm.py
fut14/__init__.py
fut14/api.py
fut14/config.py
fut14/core.py
fut14/exceptions.py
fut14/log.py
fut14/urls.py
fut14.egg-info/PKG-INFO
fut14.egg-info/SOURCES.txt
fut14.egg-info/dependency_links.txt
fut14.egg-info/requires.txt
fut14.egg-info/top_level.txt