Metadata-Version: 1.1
Name: fut14
Version: 0.0.13
Summary: fut14 is a simple library for managing Fifa 14 Ultimate Team.
Home-page: https://github.com/oczkers/fut14
Author: Piotr Staroszczyk
Author-email: piotr.staroszczyk@get24.org
License: GNU GPL v3
Download-URL: https://github.com/oczkers/fut14/releases
Keywords: fut fut14 fifa fifa14 fifa2014 ultimate team ut 14 2014 pc xbox android ios 360 ps3 playstation
Platform: any
Classifier: Development Status :: 3 - Alpha
Classifier: Intended Audience :: Developers
Classifier: Natural Language :: English
Classifier: License :: OSI Approved :: GNU General Public License v3 or later (GPLv3+)
Classifier: Programming Language :: Python
Classifier: Programming Language :: Python :: 2.6
Classifier: Programming Language :: Python :: 2.7
Classifier: Programming Language :: Python :: 3
Classifier: Programming Language :: Python :: 3.2
Classifier: Programming Language :: Python :: 3.3
Classifier: Programming Language :: Python :: Implementation :: PyPy
Classifier: Topic :: Internet :: WWW/HTTP :: Site Management
Classifier: Topic :: Software Development :: Libraries :: Python Modules
